<?xml version="1.0" encoding="utf-8" ?>
<dwsync>
<file name="basic.css" server="prevae4web.com/prevae4web.com/wwwroot/" local="129527604000000000" remote="129527604000000000" Dst="-1" />
<file name="basic_ie.css" server="prevae4web.com/prevae4web.com/wwwroot/" local="129527604000000000" remote="129527604000000000" Dst="-1" />
<file name="datepicker.css" server="prevae4web.com/prevae4web.com/wwwroot/" local="129527604000000000" remote="129527604000000000" Dst="-1" />
<file name="demo.css" server="prevae4web.com/prevae4web.com/wwwroot/" local="129527604000000000" remote="129527604000000000" Dst="-1" />
<file name="demosdatapicker.css" server="prevae4web.com/prevae4web.com/wwwroot/" local="129527604000000000" remote="129527604000000000" Dst="-1" />
<file name="estilos.css" server="prevae4web.com/prevae4web.com/wwwroot/" local="129527604000000000" remote="129527604000000000" Dst="-1" />
<file name="front.css" server="prevae4web.com/prevae4web.com/wwwroot/" local="129527604000000000" remote="129527604000000000" Dst="-1" />
<file name="jquery.jgrowl.css" server="prevae4web.com/prevae4web.com/wwwroot/" local="129527604600000000" remote="129527604600000000" Dst="-1" />
<file name="jquery.treeview.css" server="prevae4web.com/prevae4web.com/wwwroot/" local="129527604600000000" remote="129527604600000000" Dst="-1" />
<file name="layout.css" server="prevae4web.com/prevae4web.com/wwwroot/" local="129527604600000000" remote="129527604600000000" Dst="-1" />
<file name="modales.css" server="prevae4web.com/prevae4web.com/wwwroot/" local="129527604600000000" remote="129527604600000000" Dst="-1" />
<file name="reset.css" server="prevae4web.com/prevae4web.com/wwwroot/" local="129527604600000000" remote="129527604600000000" Dst="-1" />
<file name="rstrp.css" server="prevae4web.com/prevae4web.com/wwwroot/" local="129527604600000000" remote="129527604600000000" Dst="-1" />
<file name="rstrp2.css" server="prevae4web.com/prevae4web.com/wwwroot/" local="129527604600000000" remote="129527604600000000" Dst="-1" />
<file name="simplemodal.basic.css" server="prevae4web.com/prevae4web.com/wwwroot/" local="129527604600000000" remote="129527604600000000" Dst="-1" />
<file name="simplemodal.basic_ie.css" server="prevae4web.com/prevae4web.com/wwwroot/" local="129527604600000000" remote="129527604600000000" Dst="-1" />
<file name="simplemodal.css" server="prevae4web.com/prevae4web.com/wwwroot/" local="129527604600000000" remote="129527604600000000" Dst="-1" />
<file name="style.css" server="prevae4web.com/prevae4web.com/wwwroot/" local="129527604600000000" remote="129527604600000000" Dst="-1" />
<file name="ui.notify.css" server="prevae4web.com/prevae4web.com/wwwroot/" local="129527604600000000" remote="129527604600000000" Dst="-1" />
<file name="nucleo.css" server="prevae4web.com/prevae4web.com/wwwroot/" local="129449880000000000" remote="129815924400000000" Dst="-1" />
<file name="theme.css" server="prevae4web.com/prevae4web.com/wwwroot/" local="129816004443062228" remote="129815935200000000" Dst="-1" />
<file name="jquery.msgbox.css" server="prevae4web.com/prevae4web.com/wwwroot/" local="129653784000000000" remote="129818552400000000" Dst="-1" />
<file name="ui.daterangepicker.css" server="prevae4web.com/prevae4web.com/wwwroot/" local="129369842160000000" remote="129854623200000000" Dst="-1" />
<file name="basic.css" server="192.168.27.29/EucomexFE/Web/" local="129527604000000000" remote="129875658600000000" Dst="-1" />
<file name="basic_ie.css" server="192.168.27.29/EucomexFE/Web/" local="129527604000000000" remote="129875658600000000" Dst="-1" />
<file name="datepicker.css" server="192.168.27.29/EucomexFE/Web/" local="129449992800000000" remote="129875659200000000" Dst="-1" />
<file name="demo.css" server="192.168.27.29/EucomexFE/Web/" local="129527604000000000" remote="129875659200000000" Dst="-1" />
<file name="demosdatapicker.css" server="192.168.27.29/EucomexFE/Web/" local="129449992800000000" remote="129875659200000000" Dst="-1" />
<file name="estilos.css" server="192.168.27.29/EucomexFE/Web/" local="129527604000000000" remote="129875659200000000" Dst="-1" />
<file name="front.css" server="192.168.27.29/EucomexFE/Web/" local="129527604000000000" remote="129875659200000000" Dst="-1" />
<file name="jquery.jgrowl.css" server="192.168.27.29/EucomexFE/Web/" local="129527604600000000" remote="129875659200000000" Dst="-1" />
<file name="jquery.msgbox.css" server="192.168.27.29/EucomexFE/Web/" local="129653784000000000" remote="129875659200000000" Dst="-1" />
<file name="jquery.treeview.css" server="192.168.27.29/EucomexFE/Web/" local="129527604600000000" remote="129875659200000000" Dst="-1" />
<file name="layout.css" server="192.168.27.29/EucomexFE/Web/" local="129527604600000000" remote="129875659200000000" Dst="-1" />
<file name="modales.css" server="192.168.27.29/EucomexFE/Web/" local="129527604600000000" remote="129875659200000000" Dst="-1" />
<file name="nucleo.css" server="192.168.27.29/EucomexFE/Web/" local="129449880000000000" remote="129875659200000000" Dst="-1" />
<file name="reset.css" server="192.168.27.29/EucomexFE/Web/" local="129527604600000000" remote="129875659200000000" Dst="-1" />
<file name="rstrp.css" server="192.168.27.29/EucomexFE/Web/" local="129527604600000000" remote="129875659200000000" Dst="-1" />
<file name="rstrp2.css" server="192.168.27.29/EucomexFE/Web/" local="129527604600000000" remote="129875659200000000" Dst="-1" />
<file name="simplemodal.basic.css" server="192.168.27.29/EucomexFE/Web/" local="129527604600000000" remote="129875659200000000" Dst="-1" />
<file name="simplemodal.basic_ie.css" server="192.168.27.29/EucomexFE/Web/" local="129527604600000000" remote="129875659200000000" Dst="-1" />
<file name="simplemodal.css" server="192.168.27.29/EucomexFE/Web/" local="129527604600000000" remote="129875659200000000" Dst="-1" />
<file name="style.css" server="192.168.27.29/EucomexFE/Web/" local="129527604600000000" remote="129875659200000000" Dst="-1" />
<file name="theme.css" server="192.168.27.29/EucomexFE/Web/" local="129816004443062228" remote="129875659200000000" Dst="-1" />
<file name="ui.daterangepicker.css" server="192.168.27.29/EucomexFE/Web/" local="129369842160000000" remote="129875659200000000" Dst="-1" />
<file name="ui.notify.css" server="192.168.27.29/EucomexFE/Web/" local="129527604600000000" remote="129875659200000000" Dst="-1" />
<file name="xbreadcrumbs.css" server="prevae4web.com/prevae4web.com/wwwroot/" local="129884121232702267" remote="129884049000000000" Dst="-1" />
<file name="demo.css" server="54.245.122.78/IC/" local="129895605000000000" remote="129895605000000000" Dst="-1" />
<file name="front.css" server="54.245.122.78/IC/" local="129895605000000000" remote="129895605000000000" Dst="-1" />
<file name="basic.css" server="192.168.27.29" local="129527604000000000" remote="129901435200000000" Dst="-1" />
<file name="basic_ie.css" server="192.168.27.29" local="129527604000000000" remote="129901435200000000" Dst="-1" />
<file name="datepicker.css" server="192.168.27.29" local="129449992800000000" remote="129901435200000000" Dst="-1" />
<file name="demo.css" server="192.168.27.29" local="129895605000000000" remote="129901435200000000" Dst="-1" />
<file name="demosdatapicker.css" server="192.168.27.29" local="129449992800000000" remote="129901435200000000" Dst="-1" />
<file name="estilos.css" server="192.168.27.29" local="129527604000000000" remote="129901435200000000" Dst="-1" />
<file name="front.css" server="192.168.27.29" local="129895605000000000" remote="129901435200000000" Dst="-1" />
<file name="jquery.jgrowl.css" server="192.168.27.29" local="129527604600000000" remote="129901435200000000" Dst="-1" />
<file name="jquery.msgbox.css" server="192.168.27.29" local="129653784000000000" remote="129901435200000000" Dst="-1" />
<file name="jquery.treeview.css" server="192.168.27.29" local="129527604600000000" remote="129901435200000000" Dst="-1" />
<file name="layout.css" server="192.168.27.29" local="129527604600000000" remote="129901435200000000" Dst="-1" />
<file name="modales.css" server="192.168.27.29" local="129527604600000000" remote="129901435200000000" Dst="-1" />
<file name="nucleo.css" server="192.168.27.29" local="129449880000000000" remote="129901435200000000" Dst="-1" />
<file name="reset.css" server="192.168.27.29" local="129527604600000000" remote="129901435200000000" Dst="-1" />
<file name="rstrp.css" server="192.168.27.29" local="129527604600000000" remote="129901435200000000" Dst="-1" />
<file name="rstrp2.css" server="192.168.27.29" local="129527604600000000" remote="129901435200000000" Dst="-1" />
<file name="simplemodal.basic.css" server="192.168.27.29" local="129527604600000000" remote="129901435200000000" Dst="-1" />
<file name="simplemodal.basic_ie.css" server="192.168.27.29" local="129527604600000000" remote="129901435200000000" Dst="-1" />
<file name="simplemodal.css" server="192.168.27.29" local="129527604600000000" remote="129901435200000000" Dst="-1" />
<file name="style.css" server="192.168.27.29" local="129527604600000000" remote="129901435200000000" Dst="-1" />
<file name="theme.css" server="192.168.27.29" local="129816004443062228" remote="129901435200000000" Dst="-1" />
<file name="ui.daterangepicker.css" server="192.168.27.29" local="129369842160000000" remote="129901435200000000" Dst="-1" />
<file name="ui.notify.css" server="192.168.27.29" local="129527604600000000" remote="129901435200000000" Dst="-1" />
<file name="xbreadcrumbs.css" server="192.168.27.29" local="129884121232702267" remote="129901435200000000" Dst="-1" />
<file name="DivsTablas.css" server="prevae4web.com/prevae4web.com/wwwroot/" local="129884006400000000" remote="129884006400000000" Dst="-1" />
<file name="nyroModal.css" server="prevae4web.com/prevae4web.com/wwwroot/" local="129866175600000000" remote="129866175600000000" Dst="-1" />
<file name="metisMenu.css" server="ftp.iqon4web.com/prevae4web.com/wwwroot/" local="130426919409326277" remote="130426847400000000" Dst="2" />
<file name="basic.css" server="centrocomercial.ddns.net/centrocomercial/www/" local="129527604000000000" remote="130581475800000000" Dst="2" />
<file name="basic_ie.css" server="centrocomercial.ddns.net/centrocomercial/www/" local="129527604000000000" remote="130581475800000000" Dst="2" />
<file name="datepicker.css" server="centrocomercial.ddns.net/centrocomercial/www/" local="129449992800000000" remote="130581475800000000" Dst="2" />
<file name="demo.css" server="centrocomercial.ddns.net/centrocomercial/www/" local="129895605000000000" remote="130581475800000000" Dst="2" />
<file name="demosdatapicker.css" server="centrocomercial.ddns.net/centrocomercial/www/" local="129449992800000000" remote="130581475800000000" Dst="2" />
<file name="DivsTablas.css" server="centrocomercial.ddns.net/centrocomercial/www/" local="129884006400000000" remote="130581475800000000" Dst="2" />
<file name="estilos.css" server="centrocomercial.ddns.net/centrocomercial/www/" local="129527604000000000" remote="130581476400000000" Dst="2" />
<file name="front.css" server="centrocomercial.ddns.net/centrocomercial/www/" local="129895605000000000" remote="130581476400000000" Dst="2" />
<file name="icons.css" server="centrocomercial.ddns.net/centrocomercial/www/" local="130083184540000000" remote="130581476400000000" Dst="2" />
<file name="jquery.jgrowl.css" server="centrocomercial.ddns.net/centrocomercial/www/" local="129527604600000000" remote="130581476400000000" Dst="2" />
<file name="jquery.msgbox.css" server="centrocomercial.ddns.net/centrocomercial/www/" local="129653784000000000" remote="130581476400000000" Dst="2" />
<file name="jquery.treeview.css" server="centrocomercial.ddns.net/centrocomercial/www/" local="129527604600000000" remote="130581476400000000" Dst="2" />
<file name="layout.css" server="centrocomercial.ddns.net/centrocomercial/www/" local="129527604600000000" remote="130581476400000000" Dst="2" />
<file name="metisMenu.css" server="centrocomercial.ddns.net/centrocomercial/www/" local="130426919409326277" remote="130581476400000000" Dst="2" />
<file name="modales.css" server="centrocomercial.ddns.net/centrocomercial/www/" local="129527604600000000" remote="130581476400000000" Dst="2" />
<file name="nucleo.css" server="centrocomercial.ddns.net/centrocomercial/www/" local="129449880000000000" remote="130581476400000000" Dst="2" />
<file name="nyroModal.css" server="centrocomercial.ddns.net/centrocomercial/www/" local="129866175600000000" remote="130581476400000000" Dst="2" />
<file name="reset.css" server="centrocomercial.ddns.net/centrocomercial/www/" local="129527604600000000" remote="130581476400000000" Dst="2" />
<file name="rstrp.css" server="centrocomercial.ddns.net/centrocomercial/www/" local="129527604600000000" remote="130581476400000000" Dst="2" />
<file name="rstrp2.css" server="centrocomercial.ddns.net/centrocomercial/www/" local="129527604600000000" remote="130581476400000000" Dst="2" />
<file name="simplemodal.basic.css" server="centrocomercial.ddns.net/centrocomercial/www/" local="129527604600000000" remote="130581476400000000" Dst="2" />
<file name="simplemodal.basic_ie.css" server="centrocomercial.ddns.net/centrocomercial/www/" local="129527604600000000" remote="130581476400000000" Dst="2" />
<file name="simplemodal.css" server="centrocomercial.ddns.net/centrocomercial/www/" local="129527604600000000" remote="130581476400000000" Dst="2" />
<file name="style.css" server="centrocomercial.ddns.net/centrocomercial/www/" local="129527604600000000" remote="130581476400000000" Dst="2" />
<file name="theme.css" server="centrocomercial.ddns.net/centrocomercial/www/" local="129816004443062228" remote="130581476400000000" Dst="2" />
<file name="ui.daterangepicker.css" server="centrocomercial.ddns.net/centrocomercial/www/" local="129369842160000000" remote="130581476400000000" Dst="2" />
<file name="ui.notify.css" server="centrocomercial.ddns.net/centrocomercial/www/" local="129527604600000000" remote="130581476400000000" Dst="2" />
<file name="xbreadcrumbs.css" server="centrocomercial.ddns.net/centrocomercial/www/" local="129884121232702267" remote="130581476400000000" Dst="2" />
<file name="Ficha_Pindol.css" server="198.38.94.40//sherbeneFTP/Arquitecto/" local="130662102792802903" remote="130662104400000000" Dst="1" />
<file name="rstrp.css" server="198.38.94.40//sherbeneFTP/Arquitecto/" local="130555823400000000" remote="130555823400000000" Dst="1" />
<file name="jquerysctipttop.css" server="198.38.94.40//sherbeneFTP/Arquitecto/" local="130673968200000000" remote="130673968200000000" Dst="1" />
</dwsync>